[{
	"text": "Introduction",
	"ref": "sap-icon://attachment-html"

}, {
	"text": "About DSM",
	"ref": "sap-icon://attachment-html"
}, {
	"text": "DSM Programme",
	"ref": "sap-icon://attachment-html"
}
, {
	"text": "Energry Convervation",
	"ref": "sap-icon://attachment-html"
}, {
	"text": "Ceiling Fan",
	"ref": "sap-icon://attachment-html"
},
{
	"text": "Energy Audit",
	"ref": "sap-icon://attachment-html"
},
 {
	"text": "Energy Refrigerator",
	"ref": "sap-icon://attachment-html"
},
 {
	"text": "LED Tube",
	"ref": "sap-icon://attachment-html"
},

 {
	"text": "Split AC",
	"ref": "sap-icon://attachment-html"
}]